<?xml version="1.0"?>
<Task name= "51_artificialVFRRT.xml" >
	<Initialstate>
		<Object object= "plain">  0.0  0.0  0.0  0.0  0.0  1.0  0.0 </Object>
		<Object object= "plainbox_1">  0.11917346715927124  0.305869996547699  0.10000000149011612  8.659561265171044e-17  -0.7071068286895752  0.7071068286895752  3.1415927410125732 </Object>
		<Object object= "plainbox_2">  0.4216936230659485  0.7052549123764038  0.10000000149011612  8.659561265171044e-17  -0.7071068286895752  0.7071068286895752  3.1415927410125732 </Object>
		<Object object= "plainbox_3">  0.7368423938751221  0.13346558809280396  0.10000000149011612  8.659561265171044e-17  -0.7071068286895752  0.7071068286895752  3.1415927410125732 </Object>
		<Object object= "plainbox_4">  0.5311771631240845  0.5517562031745911  0.10000000149011612  8.659561265171044e-17  -0.7071068286895752  0.7071068286895752  3.1415927410125732 </Object>
		<Object object= "plainbox_5">  0.7226147055625916  0.8640543222427368  0.10000000149011612  8.659561265171044e-17  -0.7071068286895752  0.7071068286895752  3.1415927410125732 </Object>
		<Object object= "plainbox_6">  0.6095781922340393  0.9624199867248535  0.10000000149011612  8.659561265171044e-17  -0.7071068286895752  0.7071068286895752  3.1415927410125732 </Object>
		<Object object= "plainbox_7">  0.9184451699256897  0.6220871806144714  0.10000000149011612  8.659561265171044e-17  -0.7071068286895752  0.7071068286895752  3.1415927410125732 </Object>
		<Object object= "walls">  0.0  0.0  0.0  0.0  0.0  1.0  0.0 </Object>
	</Initialstate>
	<Transit>
		<Conf> 0.16783399879932404 0.3185490071773529 0.0560000017285347 8.659559941682064e-17 -0.7071070075035095 0.7071070075035095 -4.3711398944878965e-08  </Conf>
		<Conf> 0.17956799268722534 0.3228580057621002 0.0560000017285347 8.659559941682064e-17 -0.7071070075035095 0.7071070075035095 -4.3711398944878965e-08  </Conf>
		<Conf> 0.19130200147628784 0.32716599106788635 0.0560000017285347 8.659559941682064e-17 -0.7071070075035095 0.7071070075035095 -4.3711398944878965e-08  </Conf>
		<Conf> 0.20303599536418915 0.33147498965263367 0.0560000017285347 8.659559941682064e-17 -0.7071070075035095 0.7071070075035095 -4.3711398944878965e-08  </Conf>
		<Conf> 0.21477000415325165 0.335783988237381 0.0560000017285347 8.659559941682064e-17 -0.7071070075035095 0.7071070075035095 -4.3711398944878965e-08  </Conf>
		<Conf> 0.22650399804115295 0.3400929868221283 0.0560000017285347 8.659559941682064e-17 -0.7071070075035095 0.7071070075035095 -4.3711398944878965e-08  </Conf>
		<Conf> 0.23823800683021545 0.3444019854068756 0.0560000017285347 8.659559941682064e-17 -0.7071070075035095 0.7071070075035095 -4.3711398944878965e-08  </Conf>
		<Conf> 0.24997200071811676 0.34871000051498413 0.0560000017285347 8.659559941682064e-17 -0.7071070075035095 0.7071070075035095 -4.3711398944878965e-08  </Conf>
		<Conf> 0.26170599460601807 0.35301899909973145 0.0560000017285347 8.659559941682064e-17 -0.7071070075035095 0.7071070075035095 -4.3711398944878965e-08  </Conf>
		<Conf> 0.26386600732803345 0.340707004070282 0.0560000017285347 8.659559941682064e-17 -0.7071070075035095 0.7071070075035095 -4.3711398944878965e-08  </Conf>
		<Conf> 0.26602599024772644 0.3283950090408325 0.0560000017285347 8.659559941682064e-17 -0.7071070075035095 0.7071070075035095 -4.3711398944878965e-08  </Conf>
		<Conf> 0.2681860029697418 0.31608301401138306 0.0560000017285347 8.659559941682064e-17 -0.7071070075035095 0.7071070075035095 -4.3711398944878965e-08  </Conf>
		<Conf> 0.2703459858894348 0.3037709891796112 0.0560000017285347 8.659559941682064e-17 -0.7071070075035095 0.7071070075035095 -4.3711398944878965e-08  </Conf>
		<Conf> 0.2725059986114502 0.29145899415016174 0.0560000017285347 8.659559941682064e-17 -0.7071070075035095 0.7071070075035095 -4.3711398944878965e-08  </Conf>
		<Conf> 0.2746649980545044 0.2791469991207123 0.0560000017285347 8.659559941682064e-17 -0.7071070075035095 0.7071070075035095 -4.3711398944878965e-08  </Conf>
		<Conf> 0.2768250107765198 0.2668350040912628 0.0560000017285347 8.659559941682064e-17 -0.7071070075035095 0.7071070075035095 -4.3711398944878965e-08  </Conf>
		<Conf> 0.27898499369621277 0.25452300906181335 0.0560000017285347 8.659559941682064e-17 -0.7071070075035095 0.7071070075035095 -4.3711398944878965e-08  </Conf>
		<Conf> 0.2835479974746704 0.2428860068321228 0.0560000017285347 8.659559941682064e-17 -0.7071070075035095 0.7071070075035095 -4.3711398944878965e-08  </Conf>
		<Conf> 0.28811100125312805 0.23124800622463226 0.0560000017285347 8.659559941682064e-17 -0.7071070075035095 0.7071070075035095 -4.3711398944878965e-08  </Conf>
		<Conf> 0.2926740050315857 0.2196110039949417 0.0560000017285347 8.659559941682064e-17 -0.7071070075035095 0.7071070075035095 -4.3711398944878965e-08  </Conf>
		<Conf> 0.29723700881004333 0.20797300338745117 0.0560000017285347 8.659559941682064e-17 -0.7071070075035095 0.7071070075035095 -4.3711398944878965e-08  </Conf>
		<Conf> 0.3017989993095398 0.19633600115776062 0.0560000017285347 8.659559941682064e-17 -0.7071070075035095 0.7071070075035095 -4.3711398944878965e-08  </Conf>
		<Conf> 0.30636200308799744 0.18469800055027008 0.0560000017285347 8.659559941682064e-17 -0.7071070075035095 0.7071070075035095 -4.3711398944878965e-08  </Conf>
		<Conf> 0.3109250068664551 0.17306099832057953 0.0560000017285347 8.659559941682064e-17 -0.7071070075035095 0.7071070075035095 -4.3711398944878965e-08  </Conf>
		<Conf> 0.3154880106449127 0.161422997713089 0.0560000017285347 8.659559941682064e-17 -0.7071070075035095 0.7071070075035095 -4.3711398944878965e-08  </Conf>
		<Conf> 0.32560500502586365 0.15766599774360657 0.0560000017285347 8.659559941682064e-17 -0.7071070075035095 0.7071070075035095 -4.3711398944878965e-08  </Conf>
		<Conf> 0.3357219994068146 0.15390799939632416 0.0560000017285347 8.659559941682064e-17 -0.7071070075035095 0.7071070075035095 -4.3711398944878965e-08  </Conf>
		<Conf> 0.3458400070667267 0.15015099942684174 0.0560000017285347 8.659559941682064e-17 -0.7071070075035095 0.7071070075035095 -4.3711398944878965e-08  </Conf>
	</Transit>
</Task>