<?xml version="1.0"?>
<Task name= "56_artificialVFRRT.xml" >
	<Initialstate>
		<Object object= "plain">  0.0  0.0  0.0  0.0  0.0  1.0  0.0 </Object>
		<Object object= "plainbox_1">  0.7738115787506104  0.13292115926742554  0.10000000149011612  8.659561265171044e-17  -0.7071068286895752  0.7071068286895752  3.1415927410125732 </Object>
		<Object object= "plainbox_2">  0.6627780795097351  0.5792102217674255  0.10000000149011612  8.659561265171044e-17  -0.7071068286895752  0.7071068286895752  3.1415927410125732 </Object>
		<Object object= "plainbox_3">  0.046869754791259766  0.7589763402938843  0.10000000149011612  8.659561265171044e-17  -0.7071068286895752  0.7071068286895752  3.1415927410125732 </Object>
		<Object object= "plainbox_4">  0.5479704737663269  0.9487942457199097  0.10000000149011612  8.659561265171044e-17  -0.7071068286895752  0.7071068286895752  3.1415927410125732 </Object>
		<Object object= "plainbox_5">  0.14685729146003723  0.37673333287239075  0.10000000149011612  8.659561265171044e-17  -0.7071068286895752  0.7071068286895752  3.1415927410125732 </Object>
		<Object object= "plainbox_6">  0.6290134191513062  0.8023623824119568  0.10000000149011612  8.659561265171044e-17  -0.7071068286895752  0.7071068286895752  3.1415927410125732 </Object>
		<Object object= "plainbox_7">  0.6996803283691406  0.891559362411499  0.10000000149011612  8.659561265171044e-17  -0.7071068286895752  0.7071068286895752  3.1415927410125732 </Object>
		<Object object= "walls">  0.0  0.0  0.0  0.0  0.0  1.0  0.0 </Object>
	</Initialstate>
	<Transit>
		<Conf> 0.07628379762172699 0.14539200067520142 0.0560000017285347 8.659559941682064e-17 -0.7071070075035095 0.7071070075035095 -4.3711398944878965e-08  </Conf>
		<Conf> 0.08869720250368118 0.1468610018491745 0.0560000017285347 8.659559941682064e-17 -0.7071070075035095 0.7071070075035095 -4.3711398944878965e-08  </Conf>
		<Conf> 0.10111100226640701 0.14833000302314758 0.0560000017285347 8.659559941682064e-17 -0.7071070075035095 0.7071070075035095 -4.3711398944878965e-08  </Conf>
		<Conf> 0.11352399736642838 0.14979900419712067 0.0560000017285347 8.659559941682064e-17 -0.7071070075035095 0.7071070075035095 -4.3711398944878965e-08  </Conf>
		<Conf> 0.12593699991703033 0.15126800537109375 0.0560000017285347 8.659559941682064e-17 -0.7071070075035095 0.7071070075035095 -4.3711398944878965e-08  </Conf>
		<Conf> 0.13835099339485168 0.15273700654506683 0.0560000017285347 8.659559941682064e-17 -0.7071070075035095 0.7071070075035095 -4.3711398944878965e-08  </Conf>
		<Conf> 0.15076400339603424 0.15420599281787872 0.0560000017285347 8.659559941682064e-17 -0.7071070075035095 0.7071070075035095 -4.3711398944878965e-08  </Conf>
		<Conf> 0.1631779968738556 0.1556749939918518 0.0560000017285347 8.659559941682064e-17 -0.7071070075035095 0.7071070075035095 -4.3711398944878965e-08  </Conf>
		<Conf> 0.17559100687503815 0.1571429967880249 0.0560000017285347 8.659559941682064e-17 -0.7071070075035095 0.7071070075035095 -4.3711398944878965e-08  </Conf>
		<Conf> 0.1823980063199997 0.1466600000858307 0.0560000017285347 8.659559941682064e-17 -0.7071070075035095 0.7071070075035095 -4.3711398944878965e-08  </Conf>
		<Conf> 0.18920600414276123 0.1361760050058365 0.0560000017285347 8.659559941682064e-17 -0.7071070075035095 0.7071070075035095 -4.3711398944878965e-08  </Conf>
		<Conf> 0.19601300358772278 0.1256919950246811 0.0560000017285347 8.659559941682064e-17 -0.7071070075035095 0.7071070075035095 -4.3711398944878965e-08  </Conf>
		<Conf> 0.20282100141048431 0.11520899832248688 0.0560000017285347 8.659559941682064e-17 -0.7071070075035095 0.7071070075035095 -4.3711398944878965e-08  </Conf>
		<Conf> 0.20962800085544586 0.10472500324249268 0.0560000017285347 8.659559941682064e-17 -0.7071070075035095 0.7071070075035095 -4.3711398944878965e-08  </Conf>
		<Conf> 0.2164359986782074 0.09424109756946564 0.0560000017285347 8.659559941682064e-17 -0.7071070075035095 0.7071070075035095 -4.3711398944878965e-08  </Conf>
		<Conf> 0.22324299812316895 0.08375740051269531 0.0560000017285347 8.659559941682064e-17 -0.7071070075035095 0.7071070075035095 -4.3711398944878965e-08  </Conf>
		<Conf> 0.23005099594593048 0.07327359914779663 0.0560000017285347 8.659559941682064e-17 -0.7071070075035095 0.7071070075035095 -4.3711398944878965e-08  </Conf>
		<Conf> 0.24223099648952484 0.07608149945735931 0.0560000017285347 8.659559941682064e-17 -0.7071070075035095 0.7071070075035095 -4.3711398944878965e-08  </Conf>
		<Conf> 0.2544119954109192 0.07888930290937424 0.0560000017285347 8.659559941682064e-17 -0.7071070075035095 0.7071070075035095 -4.3711398944878965e-08  </Conf>
		<Conf> 0.26659199595451355 0.08169720321893692 0.0560000017285347 8.659559941682064e-17 -0.7071070075035095 0.7071070075035095 -4.3711398944878965e-08  </Conf>
		<Conf> 0.2787730097770691 0.08450499922037125 0.0560000017285347 8.659559941682064e-17 -0.7071070075035095 0.7071070075035095 -4.3711398944878965e-08  </Conf>
		<Conf> 0.29095301032066345 0.08731289952993393 0.0560000017285347 8.659559941682064e-17 -0.7071070075035095 0.7071070075035095 -4.3711398944878965e-08  </Conf>
		<Conf> 0.3031339943408966 0.09012079983949661 0.0560000017285347 8.659559941682064e-17 -0.7071070075035095 0.7071070075035095 -4.3711398944878965e-08  </Conf>
		<Conf> 0.31531399488449097 0.09292860329151154 0.0560000017285347 8.659559941682064e-17 -0.7071070075035095 0.7071070075035095 -4.3711398944878965e-08  </Conf>
		<Conf> 0.3274950087070465 0.09573650360107422 0.0560000017285347 8.659559941682064e-17 -0.7071070075035095 0.7071070075035095 -4.3711398944878965e-08  </Conf>
		<Conf> 0.3389660120010376 0.09076990187168121 0.0560000017285347 8.659559941682064e-17 -0.7071070075035095 0.7071070075035095 -4.3711398944878965e-08  </Conf>
		<Conf> 0.3504369854927063 0.08580330014228821 0.0560000017285347 8.659559941682064e-17 -0.7071070075035095 0.7071070075035095 -4.3711398944878965e-08  </Conf>
		<Conf> 0.3619079887866974 0.0808366984128952 0.0560000017285347 8.659559941682064e-17 -0.7071070075035095 0.7071070075035095 -4.3711398944878965e-08  </Conf>
		<Conf> 0.3733789920806885 0.0758700966835022 0.0560000017285347 8.659559941682064e-17 -0.7071070075035095 0.7071070075035095 -4.3711398944878965e-08  </Conf>
		<Conf> 0.38484999537467957 0.07090359926223755 0.0560000017285347 8.659559941682064e-17 -0.7071070075035095 0.7071070075035095 -4.3711398944878965e-08  </Conf>
		<Conf> 0.39632099866867065 0.06593699753284454 0.0560000017285347 8.659559941682064e-17 -0.7071070075035095 0.7071070075035095 -4.3711398944878965e-08  </Conf>
		<Conf> 0.40779200196266174 0.06097039952874184 0.0560000017285347 8.659559941682064e-17 -0.7071070075035095 0.7071070075035095 -4.3711398944878965e-08  </Conf>
		<Conf> 0.41926300525665283 0.05600380152463913 0.0560000017285347 8.659559941682064e-17 -0.7071070075035095 0.7071070075035095 -4.3711398944878965e-08  </Conf>
		<Conf> 0.42255300283432007 0.06806310266256332 0.0560000017285347 8.659559941682064e-17 -0.7071070075035095 0.7071070075035095 -4.3711398944878965e-08  </Conf>
		<Conf> 0.4258430004119873 0.08012229949235916 0.0560000017285347 8.659559941682064e-17 -0.7071070075035095 0.7071070075035095 -4.3711398944878965e-08  </Conf>
		<Conf> 0.42913299798965454 0.09218160063028336 0.0560000017285347 8.659559941682064e-17 -0.7071070075035095 0.7071070075035095 -4.3711398944878965e-08  </Conf>
		<Conf> 0.4324229955673218 0.10424099862575531 0.0560000017285347 8.659559941682064e-17 -0.7071070075035095 0.7071070075035095 -4.3711398944878965e-08  </Conf>
		<Conf> 0.435712993144989 0.11630000174045563 0.0560000017285347 8.659559941682064e-17 -0.7071070075035095 0.7071070075035095 -4.3711398944878965e-08  </Conf>
		<Conf> 0.43900299072265625 0.12835900485515594 0.0560000017285347 8.659559941682064e-17 -0.7071070075035095 0.7071070075035095 -4.3711398944878965e-08  </Conf>
		<Conf> 0.4422929883003235 0.14041900634765625 0.0560000017285347 8.659559941682064e-17 -0.7071070075035095 0.7071070075035095 -4.3711398944878965e-08  </Conf>
		<Conf> 0.4455829858779907 0.15247799456119537 0.0560000017285347 8.659559941682064e-17 -0.7071070075035095 0.7071070075035095 -4.3711398944878965e-08  </Conf>
		<Conf> 0.4509490132331848 0.1637679934501648 0.0560000017285347 8.659559941682064e-17 -0.7071070075035095 0.7071070075035095 -4.3711398944878965e-08  </Conf>
		<Conf> 0.45631399750709534 0.17505699396133423 0.0560000017285347 8.659559941682064e-17 -0.7071070075035095 0.7071070075035095 -4.3711398944878965e-08  </Conf>
		<Conf> 0.46167999505996704 0.18634699285030365 0.0560000017285347 8.659559941682064e-17 -0.7071070075035095 0.7071070075035095 -4.3711398944878965e-08  </Conf>
		<Conf> 0.46704599261283875 0.19763700664043427 0.0560000017285347 8.659559941682064e-17 -0.7071070075035095 0.7071070075035095 -4.3711398944878965e-08  </Conf>
		<Conf> 0.47241100668907166 0.2089270055294037 0.0560000017285347 8.659559941682064e-17 -0.7071070075035095 0.7071070075035095 -4.3711398944878965e-08  </Conf>
		<Conf> 0.47777700424194336 0.2202170044183731 0.0560000017285347 8.659559941682064e-17 -0.7071070075035095 0.7071070075035095 -4.3711398944878965e-08  </Conf>
		<Conf> 0.48314300179481506 0.23150700330734253 0.0560000017285347 8.659559941682064e-17 -0.7071070075035095 0.7071070075035095 -4.3711398944878965e-08  </Conf>
		<Conf> 0.4885079860687256 0.24279600381851196 0.0560000017285347 8.659559941682064e-17 -0.7071070075035095 0.7071070075035095 -4.3711398944878965e-08  </Conf>
		<Conf> 0.49463900923728943 0.2536900043487549 0.0560000017285347 8.659559941682064e-17 -0.7071070075035095 0.7071070075035095 -4.3711398944878965e-08  </Conf>
		<Conf> 0.5007699728012085 0.2645829916000366 0.0560000017285347 8.659559941682064e-17 -0.7071070075035095 0.7071070075035095 -4.3711398944878965e-08  </Conf>
		<Conf> 0.5069010257720947 0.27547600865364075 0.0560000017285347 8.659559941682064e-17 -0.7071070075035095 0.7071070075035095 -4.3711398944878965e-08  </Conf>
		<Conf> 0.5130320191383362 0.2863689959049225 0.0560000017285347 8.659559941682064e-17 -0.7071070075035095 0.7071070075035095 -4.3711398944878965e-08  </Conf>
		<Conf> 0.5191619992256165 0.2972629964351654 0.0560000017285347 8.659559941682064e-17 -0.7071070075035095 0.7071070075035095 -4.3711398944878965e-08  </Conf>
		<Conf> 0.5252929925918579 0.30815601348876953 0.0560000017285347 8.659559941682064e-17 -0.7071070075035095 0.7071070075035095 -4.3711398944878965e-08  </Conf>
		<Conf> 0.5314239859580994 0.31904900074005127 0.0560000017285347 8.659559941682064e-17 -0.7071070075035095 0.7071070075035095 -4.3711398944878965e-08  </Conf>
		<Conf> 0.5375549793243408 0.329941987991333 0.0560000017285347 8.659559941682064e-17 -0.7071070075035095 0.7071070075035095 -4.3711398944878965e-08  </Conf>
		<Conf> 0.5449849963188171 0.33999499678611755 0.0560000017285347 8.659559941682064e-17 -0.7071070075035095 0.7071070075035095 -4.3711398944878965e-08  </Conf>
		<Conf> 0.5524150133132935 0.3500469923019409 0.0560000017285347 8.659559941682064e-17 -0.7071070075035095 0.7071070075035095 -4.3711398944878965e-08  </Conf>
		<Conf> 0.5598440170288086 0.3600989878177643 0.0560000017285347 8.659559941682064e-17 -0.7071070075035095 0.7071070075035095 -4.3711398944878965e-08  </Conf>
		<Conf> 0.5672739744186401 0.37015101313591003 0.0560000017285347 8.659559941682064e-17 -0.7071070075035095 0.7071070075035095 -4.3711398944878965e-08  </Conf>
		<Conf> 0.5747039914131165 0.3802039921283722 0.0560000017285347 8.659559941682064e-17 -0.7071070075035095 0.7071070075035095 -4.3711398944878965e-08  </Conf>
		<Conf> 0.5821340084075928 0.39025598764419556 0.0560000017285347 8.659559941682064e-17 -0.7071070075035095 0.7071070075035095 -4.3711398944878965e-08  </Conf>
		<Conf> 0.5895640254020691 0.4003080129623413 0.0560000017285347 8.659559941682064e-17 -0.7071070075035095 0.7071070075035095 -4.3711398944878965e-08  </Conf>
		<Conf> 0.5969930291175842 0.4103600084781647 0.0560000017285347 8.659559941682064e-17 -0.7071070075035095 0.7071070075035095 -4.3711398944878965e-08  </Conf>
		<Conf> 0.6054840087890625 0.4195350110530853 0.0560000017285347 8.659559941682064e-17 -0.7071070075035095 0.7071070075035095 -4.3711398944878965e-08  </Conf>
		<Conf> 0.6139739751815796 0.4287090003490448 0.0560000017285347 8.659559941682064e-17 -0.7071070075035095 0.7071070075035095 -4.3711398944878965e-08  </Conf>
		<Conf> 0.6224640011787415 0.4378829896450043 0.0560000017285347 8.659559941682064e-17 -0.7071070075035095 0.7071070075035095 -4.3711398944878965e-08  </Conf>
		<Conf> 0.6309549808502197 0.44705700874328613 0.0560000017285347 8.659559941682064e-17 -0.7071070075035095 0.7071070075035095 -4.3711398944878965e-08  </Conf>
		<Conf> 0.6394450068473816 0.4562309980392456 0.0560000017285347 8.659559941682064e-17 -0.7071070075035095 0.7071070075035095 -4.3711398944878965e-08  </Conf>
		<Conf> 0.6479349732398987 0.4654049873352051 0.0560000017285347 8.659559941682064e-17 -0.7071070075035095 0.7071070075035095 -4.3711398944878965e-08  </Conf>
		<Conf> 0.6564249992370605 0.47457998991012573 0.0560000017285347 8.659559941682064e-17 -0.7071070075035095 0.7071070075035095 -4.3711398944878965e-08  </Conf>
		<Conf> 0.6649159789085388 0.4837540090084076 0.0560000017285347 8.659559941682064e-17 -0.7071070075035095 0.7071070075035095 -4.3711398944878965e-08  </Conf>
		<Conf> 0.672631025314331 0.49358901381492615 0.0560000017285347 8.659559941682064e-17 -0.7071070075035095 0.7071070075035095 -4.3711398944878965e-08  </Conf>
		<Conf> 0.6803460121154785 0.5034239888191223 0.0560000017285347 8.659559941682064e-17 -0.7071070075035095 0.7071070075035095 -4.3711398944878965e-08  </Conf>
		<Conf> 0.688060998916626 0.5132589936256409 0.0560000017285347 8.659559941682064e-17 -0.7071070075035095 0.7071070075035095 -4.3711398944878965e-08  </Conf>
		<Conf> 0.6957759857177734 0.5230939984321594 0.0560000017285347 8.659559941682064e-17 -0.7071070075035095 0.7071070075035095 -4.3711398944878965e-08  </Conf>
		<Conf> 0.7034909725189209 0.532929003238678 0.0560000017285347 8.659559941682064e-17 -0.7071070075035095 0.7071070075035095 -4.3711398944878965e-08  </Conf>
		<Conf> 0.7112060189247131 0.5427640080451965 0.0560000017285347 8.659559941682064e-17 -0.7071070075035095 0.7071070075035095 -4.3711398944878965e-08  </Conf>
		<Conf> 0.7189210057258606 0.5525990128517151 0.0560000017285347 8.659559941682064e-17 -0.7071070075035095 0.7071070075035095 -4.3711398944878965e-08  </Conf>
		<Conf> 0.7266359925270081 0.5624340176582336 0.0560000017285347 8.659559941682064e-17 -0.7071070075035095 0.7071070075035095 -4.3711398944878965e-08  </Conf>
		<Conf> 0.7293639779090881 0.5746319890022278 0.0560000017285347 8.659559941682064e-17 -0.7071070075035095 0.7071070075035095 -4.3711398944878965e-08  </Conf>
		<Conf> 0.7320929765701294 0.5868309736251831 0.0560000017285347 8.659559941682064e-17 -0.7071070075035095 0.7071070075035095 -4.3711398944878965e-08  </Conf>
		<Conf> 0.7348210215568542 0.5990300178527832 0.0560000017285347 8.659559941682064e-17 -0.7071070075035095 0.7071070075035095 -4.3711398944878965e-08  </Conf>
		<Conf> 0.7375490069389343 0.6112279891967773 0.0560000017285347 8.659559941682064e-17 -0.7071070075035095 0.7071070075035095 -4.3711398944878965e-08  </Conf>
		<Conf> 0.7402769923210144 0.6234269738197327 0.0560000017285347 8.659559941682064e-17 -0.7071070075035095 0.7071070075035095 -4.3711398944878965e-08  </Conf>
		<Conf> 0.7430059909820557 0.6356260180473328 0.0560000017285347 8.659559941682064e-17 -0.7071070075035095 0.7071070075035095 -4.3711398944878965e-08  </Conf>
		<Conf> 0.7457339763641357 0.6478239893913269 0.0560000017285347 8.659559941682064e-17 -0.7071070075035095 0.7071070075035095 -4.3711398944878965e-08  </Conf>
		<Conf> 0.7484620213508606 0.6600229740142822 0.0560000017285347 8.659559941682064e-17 -0.7071070075035095 0.7071070075035095 -4.3711398944878965e-08  </Conf>
		<Conf> 0.7596719861030579 0.6514710187911987 0.0560000017285347 8.659559941682064e-17 -0.7071070075035095 0.7071070075035095 -4.3711398944878965e-08  </Conf>
		<Conf> 0.7708809971809387 0.6429200172424316 0.0560000017285347 8.659559941682064e-17 -0.7071070075035095 0.7071070075035095 -4.3711398944878965e-08  </Conf>
		<Conf> 0.7820910215377808 0.6343680024147034 0.0560000017285347 8.659559941682064e-17 -0.7071070075035095 0.7071070075035095 -4.3711398944878965e-08  </Conf>
		<Conf> 0.7932999730110168 0.6258159875869751 0.0560000017285347 8.659559941682064e-17 -0.7071070075035095 0.7071070075035095 -4.3711398944878965e-08  </Conf>
		<Conf> 0.8045099973678589 0.617264986038208 0.0560000017285347 8.659559941682064e-17 -0.7071070075035095 0.7071070075035095 -4.3711398944878965e-08  </Conf>
		<Conf> 0.8157190084457397 0.6087129712104797 0.0560000017285347 8.659559941682064e-17 -0.7071070075035095 0.7071070075035095 -4.3711398944878965e-08  </Conf>
	</Transit>
</Task>