<?xml version="1.0"?>
<Task name= "73_artificialVFRRT.xml" >
	<Initialstate>
		<Object object= "plain">  0.0  0.0  0.0  0.0  0.0  1.0  0.0 </Object>
		<Object object= "plainbox_1">  0.15337494015693665  0.02392709255218506  0.10000000149011612  8.659561265171044e-17  -0.7071068286895752  0.7071068286895752  3.1415927410125732 </Object>
		<Object object= "plainbox_2">  0.056097596883773804  0.7928014993667603  0.10000000149011612  8.659561265171044e-17  -0.7071068286895752  0.7071068286895752  3.1415927410125732 </Object>
		<Object object= "plainbox_3">  0.9574328064918518  0.7829803824424744  0.10000000149011612  8.659561265171044e-17  -0.7071068286895752  0.7071068286895752  3.1415927410125732 </Object>
		<Object object= "plainbox_4">  0.675616443157196  0.0038644373416900635  0.10000000149011612  8.659561265171044e-17  -0.7071068286895752  0.7071068286895752  3.1415927410125732 </Object>
		<Object object= "plainbox_5">  0.4141138792037964  0.3052022159099579  0.10000000149011612  8.659561265171044e-17  -0.7071068286895752  0.7071068286895752  3.1415927410125732 </Object>
		<Object object= "plainbox_6">  0.9575455188751221  0.29055255651474  0.10000000149011612  8.659561265171044e-17  -0.7071068286895752  0.7071068286895752  3.1415927410125732 </Object>
		<Object object= "plainbox_7">  0.46908900141716003  0.6498655080795288  0.10000000149011612  8.659561265171044e-17  -0.7071068286895752  0.7071068286895752  3.1415927410125732 </Object>
		<Object object= "walls">  0.0  0.0  0.0  0.0  0.0  1.0  0.0 </Object>
	</Initialstate>
	<Transit>
		<Conf> 0.37380000948905945 0.41470301151275635 0.0560000017285347 8.659559941682064e-17 -0.7071070075035095 0.7071070075035095 -4.3711398944878965e-08  </Conf>
		<Conf> 0.3862760066986084 0.4139299988746643 0.0560000017285347 8.659559941682064e-17 -0.7071070075035095 0.7071070075035095 -4.3711398944878965e-08  </Conf>
		<Conf> 0.39875200390815735 0.41315799951553345 0.0560000017285347 8.659559941682064e-17 -0.7071070075035095 0.7071070075035095 -4.3711398944878965e-08  </Conf>
		<Conf> 0.4112280011177063 0.4123849868774414 0.0560000017285347 8.659559941682064e-17 -0.7071070075035095 0.7071070075035095 -4.3711398944878965e-08  </Conf>
		<Conf> 0.42370399832725525 0.41161200404167175 0.0560000017285347 8.659559941682064e-17 -0.7071070075035095 0.7071070075035095 -4.3711398944878965e-08  </Conf>
		<Conf> 0.4361799955368042 0.4108389914035797 0.0560000017285347 8.659559941682064e-17 -0.7071070075035095 0.7071070075035095 -4.3711398944878965e-08  </Conf>
		<Conf> 0.44865599274635315 0.41006600856781006 0.0560000017285347 8.659559941682064e-17 -0.7071070075035095 0.7071070075035095 -4.3711398944878965e-08  </Conf>
		<Conf> 0.4611319899559021 0.409292995929718 0.0560000017285347 8.659559941682064e-17 -0.7071070075035095 0.7071070075035095 -4.3711398944878965e-08  </Conf>
		<Conf> 0.47360798716545105 0.40852001309394836 0.0560000017285347 8.659559941682064e-17 -0.7071070075035095 0.7071070075035095 -4.3711398944878965e-08  </Conf>
		<Conf> 0.4756529927253723 0.42085200548171997 0.0560000017285347 8.659559941682064e-17 -0.7071070075035095 0.7071070075035095 -4.3711398944878965e-08  </Conf>
		<Conf> 0.4776979982852936 0.4331839978694916 0.0560000017285347 8.659559941682064e-17 -0.7071070075035095 0.7071070075035095 -4.3711398944878965e-08  </Conf>
		<Conf> 0.47974300384521484 0.4455150067806244 0.0560000017285347 8.659559941682064e-17 -0.7071070075035095 0.7071070075035095 -4.3711398944878965e-08  </Conf>
		<Conf> 0.4817880094051361 0.457846999168396 0.0560000017285347 8.659559941682064e-17 -0.7071070075035095 0.7071070075035095 -4.3711398944878965e-08  </Conf>
		<Conf> 0.483832985162735 0.4701780080795288 0.0560000017285347 8.659559941682064e-17 -0.7071070075035095 0.7071070075035095 -4.3711398944878965e-08  </Conf>
		<Conf> 0.48587799072265625 0.4825100004673004 0.0560000017285347 8.659559941682064e-17 -0.7071070075035095 0.7071070075035095 -4.3711398944878965e-08  </Conf>
		<Conf> 0.4879229962825775 0.494841992855072 0.0560000017285347 8.659559941682064e-17 -0.7071070075035095 0.7071070075035095 -4.3711398944878965e-08  </Conf>
		<Conf> 0.4899680018424988 0.5071730017662048 0.0560000017285347 8.659559941682064e-17 -0.7071070075035095 0.7071070075035095 -4.3711398944878965e-08  </Conf>
		<Conf> 0.49074000120162964 0.5196490287780762 0.0560000017285347 8.659559941682064e-17 -0.7071070075035095 0.7071070075035095 -4.3711398944878965e-08  </Conf>
		<Conf> 0.4915120005607605 0.5321249961853027 0.0560000017285347 8.659559941682064e-17 -0.7071070075035095 0.7071070075035095 -4.3711398944878965e-08  </Conf>
		<Conf> 0.49228501319885254 0.5446019768714905 0.0560000017285347 8.659559941682064e-17 -0.7071070075035095 0.7071070075035095 -4.3711398944878965e-08  </Conf>
		<Conf> 0.4930570125579834 0.5570780038833618 0.0560000017285347 8.659559941682064e-17 -0.7071070075035095 0.7071070075035095 -4.3711398944878965e-08  </Conf>
		<Conf> 0.49382901191711426 0.5695539712905884 0.0560000017285347 8.659559941682064e-17 -0.7071070075035095 0.7071070075035095 -4.3711398944878965e-08  </Conf>
		<Conf> 0.4946010112762451 0.5820299983024597 0.0560000017285347 8.659559941682064e-17 -0.7071070075035095 0.7071070075035095 -4.3711398944878965e-08  </Conf>
		<Conf> 0.49537399411201477 0.594506025314331 0.0560000017285347 8.659559941682064e-17 -0.7071070075035095 0.7071070075035095 -4.3711398944878965e-08  </Conf>
		<Conf> 0.49614599347114563 0.6069819927215576 0.0560000017285347 8.659559941682064e-17 -0.7071070075035095 0.7071070075035095 -4.3711398944878965e-08  </Conf>
		<Conf> 0.49733099341392517 0.6194260120391846 0.0560000017285347 8.659559941682064e-17 -0.7071070075035095 0.7071070075035095 -4.3711398944878965e-08  </Conf>
		<Conf> 0.4985159933567047 0.6318690180778503 0.0560000017285347 8.659559941682064e-17 -0.7071070075035095 0.7071070075035095 -4.3711398944878965e-08  </Conf>
		<Conf> 0.49970200657844543 0.6443129777908325 0.0560000017285347 8.659559941682064e-17 -0.7071070075035095 0.7071070075035095 -4.3711398944878965e-08  </Conf>
		<Conf> 0.5008869767189026 0.6567569971084595 0.0560000017285347 8.659559941682064e-17 -0.7071070075035095 0.7071070075035095 -4.3711398944878965e-08  </Conf>
		<Conf> 0.5020719766616821 0.6692000031471252 0.0560000017285347 8.659559941682064e-17 -0.7071070075035095 0.7071070075035095 -4.3711398944878965e-08  </Conf>
		<Conf> 0.5032579898834229 0.6816440224647522 0.0560000017285347 8.659559941682064e-17 -0.7071070075035095 0.7071070075035095 -4.3711398944878965e-08  </Conf>
		<Conf> 0.5044429898262024 0.6940879821777344 0.0560000017285347 8.659559941682064e-17 -0.7071070075035095 0.7071070075035095 -4.3711398944878965e-08  </Conf>
		<Conf> 0.5056290030479431 0.7065309882164001 0.0560000017285347 8.659559941682064e-17 -0.7071070075035095 0.7071070075035095 -4.3711398944878965e-08  </Conf>
		<Conf> 0.5067340135574341 0.7189819812774658 0.0560000017285347 8.659559941682064e-17 -0.7071070075035095 0.7071070075035095 -4.3711398944878965e-08  </Conf>
		<Conf> 0.5078399777412415 0.7314329743385315 0.0560000017285347 8.659559941682064e-17 -0.7071070075035095 0.7071070075035095 -4.3711398944878965e-08  </Conf>
		<Conf> 0.5089460015296936 0.7438840270042419 0.0560000017285347 8.659559941682064e-17 -0.7071070075035095 0.7071070075035095 -4.3711398944878965e-08  </Conf>
		<Conf> 0.5100520253181458 0.7563350200653076 0.0560000017285347 8.659559941682064e-17 -0.7071070075035095 0.7071070075035095 -4.3711398944878965e-08  </Conf>
		<Conf> 0.5111579895019531 0.7687860131263733 0.0560000017285347 8.659559941682064e-17 -0.7071070075035095 0.7071070075035095 -4.3711398944878965e-08  </Conf>
		<Conf> 0.5122640132904053 0.781237006187439 0.0560000017285347 8.659559941682064e-17 -0.7071070075035095 0.7071070075035095 -4.3711398944878965e-08  </Conf>
		<Conf> 0.5133690237998962 0.7936879992485046 0.0560000017285347 8.659559941682064e-17 -0.7071070075035095 0.7071070075035095 -4.3711398944878965e-08  </Conf>
		<Conf> 0.5144749879837036 0.8061389923095703 0.0560000017285347 8.659559941682064e-17 -0.7071070075035095 0.7071070075035095 -4.3711398944878965e-08  </Conf>
		<Conf> 0.5152429938316345 0.8186159729957581 0.0560000017285347 8.659559941682064e-17 -0.7071070075035095 0.7071070075035095 -4.3711398944878965e-08  </Conf>
		<Conf> 0.5160109996795654 0.8310920000076294 0.0560000017285347 8.659559941682064e-17 -0.7071070075035095 0.7071070075035095 -4.3711398944878965e-08  </Conf>
		<Conf> 0.5167790055274963 0.8435689806938171 0.0560000017285347 8.659559941682064e-17 -0.7071070075035095 0.7071070075035095 -4.3711398944878965e-08  </Conf>
		<Conf> 0.5175459980964661 0.8560450077056885 0.0560000017285347 8.659559941682064e-17 -0.7071070075035095 0.7071070075035095 -4.3711398944878965e-08  </Conf>
		<Conf> 0.518314003944397 0.868520975112915 0.0560000017285347 8.659559941682064e-17 -0.7071070075035095 0.7071070075035095 -4.3711398944878965e-08  </Conf>
		<Conf> 0.5190820097923279 0.8809980154037476 0.0560000017285347 8.659559941682064e-17 -0.7071070075035095 0.7071070075035095 -4.3711398944878965e-08  </Conf>
		<Conf> 0.5198500156402588 0.8934739828109741 0.0560000017285347 8.659559941682064e-17 -0.7071070075035095 0.7071070075035095 -4.3711398944878965e-08  </Conf>
		<Conf> 0.5206170082092285 0.9059510231018066 0.0560000017285347 8.659559941682064e-17 -0.7071070075035095 0.7071070075035095 -4.3711398944878965e-08  </Conf>
		<Conf> 0.5079339742660522 0.912106990814209 0.0560000017285347 8.659559941682064e-17 -0.7071070075035095 0.7071070075035095 -4.3711398944878965e-08  </Conf>
		<Conf> 0.49525099992752075 0.9182630181312561 0.0560000017285347 8.659559941682064e-17 -0.7071070075035095 0.7071070075035095 -4.3711398944878965e-08  </Conf>
	</Transit>
</Task>