<?xml version="1.0"?>
<Task name= "62_artificialVFRRT.xml" >
	<Initialstate>
		<Object object= "plain">  0.0  0.0  0.0  0.0  0.0  1.0  0.0 </Object>
		<Object object= "plainbox_1">  0.12817567586898804  0.9133417010307312  0.10000000149011612  8.659561265171044e-17  -0.7071068286895752  0.7071068286895752  3.1415927410125732 </Object>
		<Object object= "plainbox_2">  0.8704425096511841  0.9673523306846619  0.10000000149011612  8.659561265171044e-17  -0.7071068286895752  0.7071068286895752  3.1415927410125732 </Object>
		<Object object= "plainbox_3">  0.6655428409576416  0.5881503224372864  0.10000000149011612  8.659561265171044e-17  -0.7071068286895752  0.7071068286895752  3.1415927410125732 </Object>
		<Object object= "plainbox_4">  0.05662238597869873  0.6370558142662048  0.10000000149011612  8.659561265171044e-17  -0.7071068286895752  0.7071068286895752  3.1415927410125732 </Object>
		<Object object= "plainbox_5">  0.7431935667991638  0.9043254256248474  0.10000000149011612  8.659561265171044e-17  -0.7071068286895752  0.7071068286895752  3.1415927410125732 </Object>
		<Object object= "plainbox_6">  0.44154030084609985  0.9199262857437134  0.10000000149011612  8.659561265171044e-17  -0.7071068286895752  0.7071068286895752  3.1415927410125732 </Object>
		<Object object= "plainbox_7">  0.8662230968475342  0.047617435455322266  0.10000000149011612  8.659561265171044e-17  -0.7071068286895752  0.7071068286895752  3.1415927410125732 </Object>
		<Object object= "walls">  0.0  0.0  0.0  0.0  0.0  1.0  0.0 </Object>
	</Initialstate>
	<Transit>
		<Conf> 0.25350499153137207 0.8368769884109497 0.0560000017285347 8.659559941682064e-17 -0.7071070075035095 0.7071070075035095 -4.3711398944878965e-08  </Conf>
		<Conf> 0.2495100051164627 0.8250330090522766 0.0560000017285347 8.659559941682064e-17 -0.7071070075035095 0.7071070075035095 -4.3711398944878965e-08  </Conf>
		<Conf> 0.24551400542259216 0.8131890296936035 0.0560000017285347 8.659559941682064e-17 -0.7071070075035095 0.7071070075035095 -4.3711398944878965e-08  </Conf>
		<Conf> 0.24151800572872162 0.8013449907302856 0.0560000017285347 8.659559941682064e-17 -0.7071070075035095 0.7071070075035095 -4.3711398944878965e-08  </Conf>
		<Conf> 0.23752300441265106 0.7895010113716125 0.0560000017285347 8.659559941682064e-17 -0.7071070075035095 0.7071070075035095 -4.3711398944878965e-08  </Conf>
		<Conf> 0.23352700471878052 0.7776560187339783 0.0560000017285347 8.659559941682064e-17 -0.7071070075035095 0.7071070075035095 -4.3711398944878965e-08  </Conf>
		<Conf> 0.22953200340270996 0.7658119797706604 0.0560000017285347 8.659559941682064e-17 -0.7071070075035095 0.7071070075035095 -4.3711398944878965e-08  </Conf>
		<Conf> 0.22553600370883942 0.7539680004119873 0.0560000017285347 8.659559941682064e-17 -0.7071070075035095 0.7071070075035095 -4.3711398944878965e-08  </Conf>
		<Conf> 0.22154100239276886 0.7421240210533142 0.0560000017285347 8.659559941682064e-17 -0.7071070075035095 0.7071070075035095 -4.3711398944878965e-08  </Conf>
		<Conf> 0.23130400478839874 0.7343189716339111 0.0560000017285347 8.659559941682064e-17 -0.7071070075035095 0.7071070075035095 -4.3711398944878965e-08  </Conf>
		<Conf> 0.2410680055618286 0.7265130281448364 0.0560000017285347 8.659559941682064e-17 -0.7071070075035095 0.7071070075035095 -4.3711398944878965e-08  </Conf>
		<Conf> 0.2508319914340973 0.7187079787254333 0.0560000017285347 8.659559941682064e-17 -0.7071070075035095 0.7071070075035095 -4.3711398944878965e-08  </Conf>
		<Conf> 0.26059600710868835 0.710902988910675 0.0560000017285347 8.659559941682064e-17 -0.7071070075035095 0.7071070075035095 -4.3711398944878965e-08  </Conf>
		<Conf> 0.27035900950431824 0.7030979990959167 0.0560000017285347 8.659559941682064e-17 -0.7071070075035095 0.7071070075035095 -4.3711398944878965e-08  </Conf>
		<Conf> 0.2801229953765869 0.6952930092811584 0.0560000017285347 8.659559941682064e-17 -0.7071070075035095 0.7071070075035095 -4.3711398944878965e-08  </Conf>
		<Conf> 0.289887011051178 0.6874880194664001 0.0560000017285347 8.659559941682064e-17 -0.7071070075035095 0.7071070075035095 -4.3711398944878965e-08  </Conf>
		<Conf> 0.29965099692344666 0.6796830296516418 0.0560000017285347 8.659559941682064e-17 -0.7071070075035095 0.7071070075035095 -4.3711398944878965e-08  </Conf>
		<Conf> 0.297789990901947 0.6673219799995422 0.0560000017285347 8.659559941682064e-17 -0.7071070075035095 0.7071070075035095 -4.3711398944878965e-08  </Conf>
		<Conf> 0.29592999815940857 0.6549609899520874 0.0560000017285347 8.659559941682064e-17 -0.7071070075035095 0.7071070075035095 -4.3711398944878965e-08  </Conf>
		<Conf> 0.2940700054168701 0.6426010131835938 0.0560000017285347 8.659559941682064e-17 -0.7071070075035095 0.7071070075035095 -4.3711398944878965e-08  </Conf>
		<Conf> 0.29221001267433167 0.6302400231361389 0.0560000017285347 8.659559941682064e-17 -0.7071070075035095 0.7071070075035095 -4.3711398944878965e-08  </Conf>
		<Conf> 0.2903499901294708 0.6178789734840393 0.0560000017285347 8.659559941682064e-17 -0.7071070075035095 0.7071070075035095 -4.3711398944878965e-08  </Conf>
		<Conf> 0.2884899973869324 0.6055179834365845 0.0560000017285347 8.659559941682064e-17 -0.7071070075035095 0.7071070075035095 -4.3711398944878965e-08  </Conf>
		<Conf> 0.28662899136543274 0.5931569933891296 0.0560000017285347 8.659559941682064e-17 -0.7071070075035095 0.7071070075035095 -4.3711398944878965e-08  </Conf>
		<Conf> 0.2847689986228943 0.5807960033416748 0.0560000017285347 8.659559941682064e-17 -0.7071070075035095 0.7071070075035095 -4.3711398944878965e-08  </Conf>
		<Conf> 0.2858780026435852 0.5683460235595703 0.0560000017285347 8.659559941682064e-17 -0.7071070075035095 0.7071070075035095 -4.3711398944878965e-08  </Conf>
		<Conf> 0.2869870066642761 0.5558949708938599 0.0560000017285347 8.659559941682064e-17 -0.7071070075035095 0.7071070075035095 -4.3711398944878965e-08  </Conf>
		<Conf> 0.28809601068496704 0.5434439778327942 0.0560000017285347 8.659559941682064e-17 -0.7071070075035095 0.7071070075035095 -4.3711398944878965e-08  </Conf>
		<Conf> 0.28920501470565796 0.5309939980506897 0.0560000017285347 8.659559941682064e-17 -0.7071070075035095 0.7071070075035095 -4.3711398944878965e-08  </Conf>
		<Conf> 0.2903139889240265 0.518543004989624 0.0560000017285347 8.659559941682064e-17 -0.7071070075035095 0.7071070075035095 -4.3711398944878965e-08  </Conf>
		<Conf> 0.2914229929447174 0.5060920119285583 0.0560000017285347 8.659559941682064e-17 -0.7071070075035095 0.7071070075035095 -4.3711398944878965e-08  </Conf>
		<Conf> 0.2925319969654083 0.4936409890651703 0.0560000017285347 8.659559941682064e-17 -0.7071070075035095 0.7071070075035095 -4.3711398944878965e-08  </Conf>
		<Conf> 0.29364100098609924 0.4811910092830658 0.0560000017285347 8.659559941682064e-17 -0.7071070075035095 0.7071070075035095 -4.3711398944878965e-08  </Conf>
		<Conf> 0.291595995426178 0.4688589870929718 0.0560000017285347 8.659559941682064e-17 -0.7071070075035095 0.7071070075035095 -4.3711398944878965e-08  </Conf>
		<Conf> 0.2895509898662567 0.4565280079841614 0.0560000017285347 8.659559941682064e-17 -0.7071070075035095 0.7071070075035095 -4.3711398944878965e-08  </Conf>
		<Conf> 0.28750500082969666 0.4441959857940674 0.0560000017285347 8.659559941682064e-17 -0.7071070075035095 0.7071070075035095 -4.3711398944878965e-08  </Conf>
		<Conf> 0.2854599952697754 0.4318639934062958 0.0560000017285347 8.659559941682064e-17 -0.7071070075035095 0.7071070075035095 -4.3711398944878965e-08  </Conf>
		<Conf> 0.2834149897098541 0.41953301429748535 0.0560000017285347 8.659559941682064e-17 -0.7071070075035095 0.7071070075035095 -4.3711398944878965e-08  </Conf>
		<Conf> 0.28137001395225525 0.40720099210739136 0.0560000017285347 8.659559941682064e-17 -0.7071070075035095 0.7071070075035095 -4.3711398944878965e-08  </Conf>
		<Conf> 0.279325008392334 0.39487001299858093 0.0560000017285347 8.659559941682064e-17 -0.7071070075035095 0.7071070075035095 -4.3711398944878965e-08  </Conf>
		<Conf> 0.2772800028324127 0.38253799080848694 0.0560000017285347 8.659559941682064e-17 -0.7071070075035095 0.7071070075035095 -4.3711398944878965e-08  </Conf>
		<Conf> 0.279464989900589 0.3702299892902374 0.0560000017285347 8.659559941682064e-17 -0.7071070075035095 0.7071070075035095 -4.3711398944878965e-08  </Conf>
		<Conf> 0.28164899349212646 0.3579230010509491 0.0560000017285347 8.659559941682064e-17 -0.7071070075035095 0.7071070075035095 -4.3711398944878965e-08  </Conf>
		<Conf> 0.28383299708366394 0.3456149995326996 0.0560000017285347 8.659559941682064e-17 -0.7071070075035095 0.7071070075035095 -4.3711398944878965e-08  </Conf>
		<Conf> 0.2860170006752014 0.3333069980144501 0.0560000017285347 8.659559941682064e-17 -0.7071070075035095 0.7071070075035095 -4.3711398944878965e-08  </Conf>
		<Conf> 0.2882010042667389 0.32100000977516174 0.0560000017285347 8.659559941682064e-17 -0.7071070075035095 0.7071070075035095 -4.3711398944878965e-08  </Conf>
		<Conf> 0.29038599133491516 0.30869200825691223 0.0560000017285347 8.659559941682064e-17 -0.7071070075035095 0.7071070075035095 -4.3711398944878965e-08  </Conf>
		<Conf> 0.29256999492645264 0.2963840067386627 0.0560000017285347 8.659559941682064e-17 -0.7071070075035095 0.7071070075035095 -4.3711398944878965e-08  </Conf>
		<Conf> 0.2947539985179901 0.284076988697052 0.0560000017285347 8.659559941682064e-17 -0.7071070075035095 0.7071070075035095 -4.3711398944878965e-08  </Conf>
		<Conf> 0.30188798904418945 0.2738119959831238 0.0560000017285347 8.659559941682064e-17 -0.7071070075035095 0.7071070075035095 -4.3711398944878965e-08  </Conf>
		<Conf> 0.3090220093727112 0.26354798674583435 0.0560000017285347 8.659559941682064e-17 -0.7071070075035095 0.7071070075035095 -4.3711398944878965e-08  </Conf>
		<Conf> 0.3161559998989105 0.2532840073108673 0.0560000017285347 8.659559941682064e-17 -0.7071070075035095 0.7071070075035095 -4.3711398944878965e-08  </Conf>
		<Conf> 0.32328999042510986 0.2430189996957779 0.0560000017285347 8.659559941682064e-17 -0.7071070075035095 0.7071070075035095 -4.3711398944878965e-08  </Conf>
		<Conf> 0.3304240107536316 0.23275500535964966 0.0560000017285347 8.659559941682064e-17 -0.7071070075035095 0.7071070075035095 -4.3711398944878965e-08  </Conf>
		<Conf> 0.33755800127983093 0.22249099612236023 0.0560000017285347 8.659559941682064e-17 -0.7071070075035095 0.7071070075035095 -4.3711398944878965e-08  </Conf>
		<Conf> 0.3446919918060303 0.212227001786232 0.0560000017285347 8.659559941682064e-17 -0.7071070075035095 0.7071070075035095 -4.3711398944878965e-08  </Conf>
		<Conf> 0.351826012134552 0.20196199417114258 0.0560000017285347 8.659559941682064e-17 -0.7071070075035095 0.7071070075035095 -4.3711398944878965e-08  </Conf>
		<Conf> 0.3579080104827881 0.1910420060157776 0.0560000017285347 8.659559941682064e-17 -0.7071070075035095 0.7071070075035095 -4.3711398944878965e-08  </Conf>
		<Conf> 0.36399000883102417 0.18012100458145142 0.0560000017285347 8.659559941682064e-17 -0.7071070075035095 0.7071070075035095 -4.3711398944878965e-08  </Conf>
		<Conf> 0.3700709939002991 0.16920000314712524 0.0560000017285347 8.659559941682064e-17 -0.7071070075035095 0.7071070075035095 -4.3711398944878965e-08  </Conf>
		<Conf> 0.37615299224853516 0.15827900171279907 0.0560000017285347 8.659559941682064e-17 -0.7071070075035095 0.7071070075035095 -4.3711398944878965e-08  </Conf>
		<Conf> 0.38223499059677124 0.1473580002784729 0.0560000017285347 8.659559941682064e-17 -0.7071070075035095 0.7071070075035095 -4.3711398944878965e-08  </Conf>
		<Conf> 0.38831600546836853 0.13643799722194672 0.0560000017285347 8.659559941682064e-17 -0.7071070075035095 0.7071070075035095 -4.3711398944878965e-08  </Conf>
		<Conf> 0.3943980038166046 0.12551699578762054 0.0560000017285347 8.659559941682064e-17 -0.7071070075035095 0.7071070075035095 -4.3711398944878965e-08  </Conf>
		<Conf> 0.4004789888858795 0.11459600180387497 0.0560000017285347 8.659559941682064e-17 -0.7071070075035095 0.7071070075035095 -4.3711398944878965e-08  </Conf>
		<Conf> 0.4082280099391937 0.12440499663352966 0.0560000017285347 8.659559941682064e-17 -0.7071070075035095 0.7071070075035095 -4.3711398944878965e-08  </Conf>
		<Conf> 0.41597700119018555 0.13421300053596497 0.0560000017285347 8.659559941682064e-17 -0.7071070075035095 0.7071070075035095 -4.3711398944878965e-08  </Conf>
		<Conf> 0.42372599244117737 0.14402200281620026 0.0560000017285347 8.659559941682064e-17 -0.7071070075035095 0.7071070075035095 -4.3711398944878965e-08  </Conf>
		<Conf> 0.4314740002155304 0.15383000671863556 0.0560000017285347 8.659559941682064e-17 -0.7071070075035095 0.7071070075035095 -4.3711398944878965e-08  </Conf>
		<Conf> 0.4392229914665222 0.16363899409770966 0.0560000017285347 8.659559941682064e-17 -0.7071070075035095 0.7071070075035095 -4.3711398944878965e-08  </Conf>
		<Conf> 0.4469720125198364 0.17344699800014496 0.0560000017285347 8.659559941682064e-17 -0.7071070075035095 0.7071070075035095 -4.3711398944878965e-08  </Conf>
		<Conf> 0.45472100377082825 0.18325600028038025 0.0560000017285347 8.659559941682064e-17 -0.7071070075035095 0.7071070075035095 -4.3711398944878965e-08  </Conf>
		<Conf> 0.4624690115451813 0.19306400418281555 0.0560000017285347 8.659559941682064e-17 -0.7071070075035095 0.7071070075035095 -4.3711398944878965e-08  </Conf>
		<Conf> 0.4711489975452423 0.20205900073051453 0.0560000017285347 8.659559941682064e-17 -0.7071070075035095 0.7071070075035095 -4.3711398944878965e-08  </Conf>
		<Conf> 0.47982901334762573 0.2110539972782135 0.0560000017285347 8.659559941682064e-17 -0.7071070075035095 0.7071070075035095 -4.3711398944878965e-08  </Conf>
		<Conf> 0.48850899934768677 0.22004899382591248 0.0560000017285347 8.659559941682064e-17 -0.7071070075035095 0.7071070075035095 -4.3711398944878965e-08  </Conf>
		<Conf> 0.4971889853477478 0.22904400527477264 0.0560000017285347 8.659559941682064e-17 -0.7071070075035095 0.7071070075035095 -4.3711398944878965e-08  </Conf>
		<Conf> 0.5058689713478088 0.23803900182247162 0.0560000017285347 8.659559941682064e-17 -0.7071070075035095 0.7071070075035095 -4.3711398944878965e-08  </Conf>
		<Conf> 0.5145490169525146 0.2470329999923706 0.0560000017285347 8.659559941682064e-17 -0.7071070075035095 0.7071070075035095 -4.3711398944878965e-08  </Conf>
		<Conf> 0.5232290029525757 0.2560279965400696 0.0560000017285347 8.659559941682064e-17 -0.7071070075035095 0.7071070075035095 -4.3711398944878965e-08  </Conf>
		<Conf> 0.5319089889526367 0.26502299308776855 0.0560000017285347 8.659559941682064e-17 -0.7071070075035095 0.7071070075035095 -4.3711398944878965e-08  </Conf>
		<Conf> 0.5410339832305908 0.27356600761413574 0.0560000017285347 8.659559941682064e-17 -0.7071070075035095 0.7071070075035095 -4.3711398944878965e-08  </Conf>
		<Conf> 0.5501589775085449 0.28210899233818054 0.0560000017285347 8.659559941682064e-17 -0.7071070075035095 0.7071070075035095 -4.3711398944878965e-08  </Conf>
		<Conf> 0.559283971786499 0.2906529903411865 0.0560000017285347 8.659559941682064e-17 -0.7071070075035095 0.7071070075035095 -4.3711398944878965e-08  </Conf>
		<Conf> 0.5684090256690979 0.2991960048675537 0.0560000017285347 8.659559941682064e-17 -0.7071070075035095 0.7071070075035095 -4.3711398944878965e-08  </Conf>
		<Conf> 0.577534019947052 0.3077389895915985 0.0560000017285347 8.659559941682064e-17 -0.7071070075035095 0.7071070075035095 -4.3711398944878965e-08  </Conf>
		<Conf> 0.5866590142250061 0.3162820041179657 0.0560000017285347 8.659559941682064e-17 -0.7071070075035095 0.7071070075035095 -4.3711398944878965e-08  </Conf>
		<Conf> 0.5957840085029602 0.3248249888420105 0.0560000017285347 8.659559941682064e-17 -0.7071070075035095 0.7071070075035095 -4.3711398944878965e-08  </Conf>
		<Conf> 0.6049090027809143 0.3333689868450165 0.0560000017285347 8.659559941682064e-17 -0.7071070075035095 0.7071070075035095 -4.3711398944878965e-08  </Conf>
		<Conf> 0.6162089705467224 0.33871299028396606 0.0560000017285347 8.659559941682064e-17 -0.7071070075035095 0.7071070075035095 -4.3711398944878965e-08  </Conf>
		<Conf> 0.6275089979171753 0.34405699372291565 0.0560000017285347 8.659559941682064e-17 -0.7071070075035095 0.7071070075035095 -4.3711398944878965e-08  </Conf>
		<Conf> 0.6388090252876282 0.34940099716186523 0.0560000017285347 8.659559941682064e-17 -0.7071070075035095 0.7071070075035095 -4.3711398944878965e-08  </Conf>
		<Conf> 0.6501089930534363 0.354746013879776 0.0560000017285347 8.659559941682064e-17 -0.7071070075035095 0.7071070075035095 -4.3711398944878965e-08  </Conf>
		<Conf> 0.661408007144928 0.3600899875164032 0.0560000017285347 8.659559941682064e-17 -0.7071070075035095 0.7071070075035095 -4.3711398944878965e-08  </Conf>
		<Conf> 0.6727079749107361 0.3654339909553528 0.0560000017285347 8.659559941682064e-17 -0.7071070075035095 0.7071070075035095 -4.3711398944878965e-08  </Conf>
		<Conf> 0.684008002281189 0.37077799439430237 0.0560000017285347 8.659559941682064e-17 -0.7071070075035095 0.7071070075035095 -4.3711398944878965e-08  </Conf>
		<Conf> 0.6953080296516418 0.37612301111221313 0.0560000017285347 8.659559941682064e-17 -0.7071070075035095 0.7071070075035095 -4.3711398944878965e-08  </Conf>
		<Conf> 0.6992059946060181 0.3642460107803345 0.0560000017285347 8.659559941682064e-17 -0.7071070075035095 0.7071070075035095 -4.3711398944878965e-08  </Conf>
		<Conf> 0.7031040191650391 0.3523690104484558 0.0560000017285347 8.659559941682064e-17 -0.7071070075035095 0.7071070075035095 -4.3711398944878965e-08  </Conf>
		<Conf> 0.7070019841194153 0.34049299359321594 0.0560000017285347 8.659559941682064e-17 -0.7071070075035095 0.7071070075035095 -4.3711398944878965e-08  </Conf>
		<Conf> 0.7109010219573975 0.3286159932613373 0.0560000017285347 8.659559941682064e-17 -0.7071070075035095 0.7071070075035095 -4.3711398944878965e-08  </Conf>
		<Conf> 0.7147989869117737 0.3167389929294586 0.0560000017285347 8.659559941682064e-17 -0.7071070075035095 0.7071070075035095 -4.3711398944878965e-08  </Conf>
		<Conf> 0.7186970114707947 0.30486300587654114 0.0560000017285347 8.659559941682064e-17 -0.7071070075035095 0.7071070075035095 -4.3711398944878965e-08  </Conf>
		<Conf> 0.7225949764251709 0.2929860055446625 0.0560000017285347 8.659559941682064e-17 -0.7071070075035095 0.7071070075035095 -4.3711398944878965e-08  </Conf>
		<Conf> 0.7264930009841919 0.2811090052127838 0.0560000017285347 8.659559941682064e-17 -0.7071070075035095 0.7071070075035095 -4.3711398944878965e-08  </Conf>
		<Conf> 0.7389249801635742 0.28240999579429626 0.0560000017285347 8.659559941682064e-17 -0.7071070075035095 0.7071070075035095 -4.3711398944878965e-08  </Conf>
		<Conf> 0.7513570189476013 0.2837100028991699 0.0560000017285347 8.659559941682064e-17 -0.7071070075035095 0.7071070075035095 -4.3711398944878965e-08  </Conf>
		<Conf> 0.7637889981269836 0.2850100100040436 0.0560000017285347 8.659559941682064e-17 -0.7071070075035095 0.7071070075035095 -4.3711398944878965e-08  </Conf>
		<Conf> 0.7762219905853271 0.28630998730659485 0.0560000017285347 8.659559941682064e-17 -0.7071070075035095 0.7071070075035095 -4.3711398944878965e-08  </Conf>
		<Conf> 0.7886540293693542 0.2876099944114685 0.0560000017285347 8.659559941682064e-17 -0.7071070075035095 0.7071070075035095 -4.3711398944878965e-08  </Conf>
		<Conf> 0.8010860085487366 0.28891101479530334 0.0560000017285347 8.659559941682064e-17 -0.7071070075035095 0.7071070075035095 -4.3711398944878965e-08  </Conf>
		<Conf> 0.8135179877281189 0.2902109920978546 0.0560000017285347 8.659559941682064e-17 -0.7071070075035095 0.7071070075035095 -4.3711398944878965e-08  </Conf>
		<Conf> 0.825950026512146 0.29151099920272827 0.0560000017285347 8.659559941682064e-17 -0.7071070075035095 0.7071070075035095 -4.3711398944878965e-08  </Conf>
		<Conf> 0.8327429890632629 0.28065600991249084 0.0560000017285347 8.659559941682064e-17 -0.7071070075035095 0.7071070075035095 -4.3711398944878965e-08  </Conf>
		<Conf> 0.8395360112190247 0.26980099081993103 0.0560000017285347 8.659559941682064e-17 -0.7071070075035095 0.7071070075035095 -4.3711398944878965e-08  </Conf>
		<Conf> 0.8463289737701416 0.2589460015296936 0.0560000017285347 8.659559941682064e-17 -0.7071070075035095 0.7071070075035095 -4.3711398944878965e-08  </Conf>
		<Conf> 0.8531219959259033 0.24809099733829498 0.0560000017285347 8.659559941682064e-17 -0.7071070075035095 0.7071070075035095 -4.3711398944878965e-08  </Conf>
		<Conf> 0.859915018081665 0.23723599314689636 0.0560000017285347 8.659559941682064e-17 -0.7071070075035095 0.7071070075035095 -4.3711398944878965e-08  </Conf>
	</Transit>
</Task>