<?xml version="1.0"?>
<Task name= "62_artificialVFRRT.xml" >
	<Initialstate>
		<Object object= "plain">  0.0  0.0  0.0  0.0  0.0  1.0  0.0 </Object>
		<Object object= "plainbox_1">  0.12817567586898804  0.9133417010307312  0.10000000149011612  8.659561265171044e-17  -0.7071068286895752  0.7071068286895752  3.1415927410125732 </Object>
		<Object object= "plainbox_2">  0.8704425096511841  0.9673523306846619  0.10000000149011612  8.659561265171044e-17  -0.7071068286895752  0.7071068286895752  3.1415927410125732 </Object>
		<Object object= "plainbox_3">  0.6655428409576416  0.5881503224372864  0.10000000149011612  8.659561265171044e-17  -0.7071068286895752  0.7071068286895752  3.1415927410125732 </Object>
		<Object object= "plainbox_4">  0.05662238597869873  0.6370558142662048  0.10000000149011612  8.659561265171044e-17  -0.7071068286895752  0.7071068286895752  3.1415927410125732 </Object>
		<Object object= "plainbox_5">  0.7431935667991638  0.9043254256248474  0.10000000149011612  8.659561265171044e-17  -0.7071068286895752  0.7071068286895752  3.1415927410125732 </Object>
		<Object object= "plainbox_6">  0.44154030084609985  0.9199262857437134  0.10000000149011612  8.659561265171044e-17  -0.7071068286895752  0.7071068286895752  3.1415927410125732 </Object>
		<Object object= "plainbox_7">  0.8662230968475342  0.047617435455322266  0.10000000149011612  8.659561265171044e-17  -0.7071068286895752  0.7071068286895752  3.1415927410125732 </Object>
		<Object object= "walls">  0.0  0.0  0.0  0.0  0.0  1.0  0.0 </Object>
	</Initialstate>
	<Transit>
		<Conf> 0.8244580030441284 0.7250019907951355 0.0560000017285347 8.659559941682064e-17 -0.7071070075035095 0.7071070075035095 -4.3711398944878965e-08  </Conf>
		<Conf> 0.8360249996185303 0.7202630043029785 0.0560000017285347 8.659559941682064e-17 -0.7071070075035095 0.7071070075035095 -4.3711398944878965e-08  </Conf>
		<Conf> 0.8475919961929321 0.7155240178108215 0.0560000017285347 8.659559941682064e-17 -0.7071070075035095 0.7071070075035095 -4.3711398944878965e-08  </Conf>
		<Conf> 0.859158992767334 0.7107849717140198 0.0560000017285347 8.659559941682064e-17 -0.7071070075035095 0.7071070075035095 -4.3711398944878965e-08  </Conf>
		<Conf> 0.8707259893417358 0.7060459852218628 0.0560000017285347 8.659559941682064e-17 -0.7071070075035095 0.7071070075035095 -4.3711398944878965e-08  </Conf>
		<Conf> 0.8822929859161377 0.7013069987297058 0.0560000017285347 8.659559941682064e-17 -0.7071070075035095 0.7071070075035095 -4.3711398944878965e-08  </Conf>
		<Conf> 0.8938599824905396 0.69656902551651 0.0560000017285347 8.659559941682064e-17 -0.7071070075035095 0.7071070075035095 -4.3711398944878965e-08  </Conf>
		<Conf> 0.9054269790649414 0.6918299794197083 0.0560000017285347 8.659559941682064e-17 -0.7071070075035095 0.7071070075035095 -4.3711398944878965e-08  </Conf>
		<Conf> 0.9169930219650269 0.6870909929275513 0.0560000017285347 8.659559941682064e-17 -0.7071070075035095 0.7071070075035095 -4.3711398944878965e-08  </Conf>
		<Conf> 0.9047899842262268 0.6897979974746704 0.0560000017285347 8.659559941682064e-17 -0.7071070075035095 0.7071070075035095 -4.3711398944878965e-08  </Conf>
		<Conf> 0.8925870060920715 0.6925060153007507 0.0560000017285347 8.659559941682064e-17 -0.7071070075035095 0.7071070075035095 -4.3711398944878965e-08  </Conf>
		<Conf> 0.8803840279579163 0.6952130198478699 0.0560000017285347 8.659559941682064e-17 -0.7071070075035095 0.7071070075035095 -4.3711398944878965e-08  </Conf>
		<Conf> 0.868179976940155 0.697920024394989 0.0560000017285347 8.659559941682064e-17 -0.7071070075035095 0.7071070075035095 -4.3711398944878965e-08  </Conf>
		<Conf> 0.8559769988059998 0.7006279826164246 0.0560000017285347 8.659559941682064e-17 -0.7071070075035095 0.7071070075035095 -4.3711398944878965e-08  </Conf>
		<Conf> 0.8437740206718445 0.7033349871635437 0.0560000017285347 8.659559941682064e-17 -0.7071070075035095 0.7071070075035095 -4.3711398944878965e-08  </Conf>
		<Conf> 0.831570029258728 0.7060419917106628 0.0560000017285347 8.659559941682064e-17 -0.7071070075035095 0.7071070075035095 -4.3711398944878965e-08  </Conf>
		<Conf> 0.819366991519928 0.708748996257782 0.0560000017285347 8.659559941682064e-17 -0.7071070075035095 0.7071070075035095 -4.3711398944878965e-08  </Conf>
		<Conf> 0.807856023311615 0.7136229872703552 0.0560000017285347 8.659559941682064e-17 -0.7071070075035095 0.7071070075035095 -4.3711398944878965e-08  </Conf>
		<Conf> 0.7963460087776184 0.7184969782829285 0.0560000017285347 8.659559941682064e-17 -0.7071070075035095 0.7071070075035095 -4.3711398944878965e-08  </Conf>
		<Conf> 0.7848349809646606 0.7233710289001465 0.0560000017285347 8.659559941682064e-17 -0.7071070075035095 0.7071070075035095 -4.3711398944878965e-08  </Conf>
		<Conf> 0.7733240127563477 0.7282450199127197 0.0560000017285347 8.659559941682064e-17 -0.7071070075035095 0.7071070075035095 -4.3711398944878965e-08  </Conf>
		<Conf> 0.7618139982223511 0.733119010925293 0.0560000017285347 8.659559941682064e-17 -0.7071070075035095 0.7071070075035095 -4.3711398944878965e-08  </Conf>
		<Conf> 0.7503029704093933 0.7379930019378662 0.0560000017285347 8.659559941682064e-17 -0.7071070075035095 0.7071070075035095 -4.3711398944878965e-08  </Conf>
		<Conf> 0.7387930154800415 0.7428669929504395 0.0560000017285347 8.659559941682064e-17 -0.7071070075035095 0.7071070075035095 -4.3711398944878965e-08  </Conf>
		<Conf> 0.7272819876670837 0.7477409839630127 0.0560000017285347 8.659559941682064e-17 -0.7071070075035095 0.7071070075035095 -4.3711398944878965e-08  </Conf>
		<Conf> 0.7153859734535217 0.751579999923706 0.0560000017285347 8.659559941682064e-17 -0.7071070075035095 0.7071070075035095 -4.3711398944878965e-08  </Conf>
		<Conf> 0.7034900188446045 0.7554200291633606 0.0560000017285347 8.659559941682064e-17 -0.7071070075035095 0.7071070075035095 -4.3711398944878965e-08  </Conf>
		<Conf> 0.6915950179100037 0.7592589855194092 0.0560000017285347 8.659559941682064e-17 -0.7071070075035095 0.7071070075035095 -4.3711398944878965e-08  </Conf>
		<Conf> 0.6796990036964417 0.7630980014801025 0.0560000017285347 8.659559941682064e-17 -0.7071070075035095 0.7071070075035095 -4.3711398944878965e-08  </Conf>
		<Conf> 0.6678029894828796 0.7669379711151123 0.0560000017285347 8.659559941682064e-17 -0.7071070075035095 0.7071070075035095 -4.3711398944878965e-08  </Conf>
		<Conf> 0.6559069752693176 0.7707769870758057 0.0560000017285347 8.659559941682064e-17 -0.7071070075035095 0.7071070075035095 -4.3711398944878965e-08  </Conf>
		<Conf> 0.6440119743347168 0.7746170163154602 0.0560000017285347 8.659559941682064e-17 -0.7071070075035095 0.7071070075035095 -4.3711398944878965e-08  </Conf>
		<Conf> 0.6321160197257996 0.7784559726715088 0.0560000017285347 8.659559941682064e-17 -0.7071070075035095 0.7071070075035095 -4.3711398944878965e-08  </Conf>
		<Conf> 0.6211640238761902 0.7724310159683228 0.0560000017285347 8.659559941682064e-17 -0.7071070075035095 0.7071070075035095 -4.3711398944878965e-08  </Conf>
		<Conf> 0.6102110147476196 0.7664070129394531 0.0560000017285347 8.659559941682064e-17 -0.7071070075035095 0.7071070075035095 -4.3711398944878965e-08  </Conf>
		<Conf> 0.5992590188980103 0.7603819966316223 0.0560000017285347 8.659559941682064e-17 -0.7071070075035095 0.7071070075035095 -4.3711398944878965e-08  </Conf>
		<Conf> 0.5883070230484009 0.7543569803237915 0.0560000017285347 8.659559941682064e-17 -0.7071070075035095 0.7071070075035095 -4.3711398944878965e-08  </Conf>
		<Conf> 0.5773550271987915 0.7483320236206055 0.0560000017285347 8.659559941682064e-17 -0.7071070075035095 0.7071070075035095 -4.3711398944878965e-08  </Conf>
		<Conf> 0.566402018070221 0.7423070073127747 0.0560000017285347 8.659559941682064e-17 -0.7071070075035095 0.7071070075035095 -4.3711398944878965e-08  </Conf>
		<Conf> 0.5554500222206116 0.736283004283905 0.0560000017285347 8.659559941682064e-17 -0.7071070075035095 0.7071070075035095 -4.3711398944878965e-08  </Conf>
		<Conf> 0.5444980263710022 0.7302579879760742 0.0560000017285347 8.659559941682064e-17 -0.7071070075035095 0.7071070075035095 -4.3711398944878965e-08  </Conf>
		<Conf> 0.5354970097541809 0.720337986946106 0.0560000017285347 8.659559941682064e-17 -0.7071070075035095 0.7071070075035095 -4.3711398944878965e-08  </Conf>
		<Conf> 0.5264959931373596 0.7104169726371765 0.0560000017285347 8.659559941682064e-17 -0.7071070075035095 0.7071070075035095 -4.3711398944878965e-08  </Conf>
	</Transit>
</Task>